odoo/addons/account_payment_order_operating_unit/__init__.py
odoo/addons/account_payment_order_operating_unit/__manifest__.py
odoo/addons/account_payment_order_operating_unit/models/__init__.py
odoo/addons/account_payment_order_operating_unit/models/account_payment_line.py
odoo/addons/account_payment_order_operating_unit/models/account_payment_order.py
odoo/addons/account_payment_order_operating_unit/models/bank_payment_line.py
odoo/addons/account_payment_order_operating_unit/security/ir.model.access.csv
odoo/addons/account_payment_order_operating_unit/views/account_payment_line.xml
odoo12_addon_account_payment_order_operating_unit-12.0.0.0.4.dist-info/METADATA
odoo12_addon_account_payment_order_operating_unit-12.0.0.0.4.dist-info/WHEEL
odoo12_addon_account_payment_order_operating_unit-12.0.0.0.4.dist-info/top_level.txt
odoo12_addon_account_payment_order_operating_unit-12.0.0.0.4.dist-info/RECORD
