Metadata-Version: 2.1
Name: odoo12-addon-account-payment-order-operating-unit
Version: 12.0.0.0.4
Summary: Configuration to properly relate payment orders and operating units
Home-page: https://git.coopdevs.org/coopdevs/odoo/odoo-addons/enhancements-operating-unit
Author: Coopdevs Treball SCCL
Classifier: Programming Language :: Python
Classifier: Framework :: Odoo
Classifier: Framework :: Odoo :: 12.0
Requires-Python: >=3.5
Requires-Dist: odoo12-addon-account-banking-sepa-direct-debit
Requires-Dist: odoo12-addon-account-operating-unit
Requires-Dist: odoo12-addon-account-payment-order
Requires-Dist: odoo12-addon-operating-unit
Requires-Dist: odoo (<12.1dev,>=12.0a)
